pyterminalclock/__init__.py
pyterminalclock/main.py
pyterminalclock-0.5.0.dist-info/METADATA
pyterminalclock-0.5.0.dist-info/WHEEL
pyterminalclock-0.5.0.dist-info/entry_points.txt
pyterminalclock-0.5.0.dist-info/RECORD
