Metadata-Version: 2.4
Name: pyterminalclock
Version: 0.5.0
Summary: Add your description here
Author-email: ffalcon31415 <77492177+ffalcon31415@users.noreply.github.com>
Requires-Python: >=3.9
Requires-Dist: pyfiglet>=1.0.2
